{
 "actions": [],
 "allow_rename": 1,
 "creation": "2024-08-23 07:53:12.582101",
 "doctype": "DocType",
 "editable_grid": 1,
 "engine": "InnoDB",
 "field_order": [
  "budget_expense_account",
  "total_requested_amount",
  "total_approved_amount",
  "column_break_mwie",
  "difference",
  "total_available_balance",
  "budget_type",
  "section_break_zdnm",
  "economic_number",
  "column_break_dwhc",
  "classifications"
 ],
 "fields": [
  {
   "fieldname": "difference",
   "fieldtype": "Currency",
   "in_list_view": 1,
   "label": "Difference",
   "precision": "2",
   "read_only": 1
  },
  {
   "fieldname": "budget_expense_account",
   "fieldtype": "Link",
   "in_list_view": 1,
   "label": "Account Name",
   "options": "Account",
   "read_only": 1
  },
  {
   "fieldname": "total_requested_amount",
   "fieldtype": "Currency",
   "in_list_view": 1,
   "label": "Total Requested Amt",
   "precision": "2",
   "read_only": 1
  },
  {
   "fieldname": "total_approved_amount",
   "fieldtype": "Currency",
   "in_list_view": 1,
   "label": "Total Approved Amt",
   "precision": "2"
  },
  {
   "fieldname": "total_available_balance",
   "fieldtype": "Currency",
   "in_list_view": 1,
   "label": "Total Available Balance",
   "precision": "2"
  },
  {
   "fieldname": "economic_number",
   "fieldtype": "Data",
   "label": "Economic Number",
   "read_only": 1
  },
  {
   "fetch_from": "budget_expense_account.custom_classifications",
   "fieldname": "classifications",
   "fieldtype": "Link",
   "label": "Classifications",
   "options": "Classifications ST",
   "read_only": 1
  },
  {
   "fieldname": "column_break_mwie",
   "fieldtype": "Column Break"
  },
  {
   "fieldname": "section_break_zdnm",
   "fieldtype": "Section Break"
  },
  {
   "fieldname": "column_break_dwhc",
   "fieldtype": "Column Break"
  },
  {
   "default": "Requested",
   "fieldname": "budget_type",
   "fieldtype": "Select",
   "label": "Budget Type",
   "options": "Requested\nNot Requested",
   "read_only": 1
  }
 ],
 "index_web_pages_for_search": 1,
 "istable": 1,
 "links": [],
 "modified": "2025-02-19 08:19:54.299889",
 "modified_by": "Administrator",
 "module": "Stats",
 "name": "Accumulative Budget Details ST",
 "owner": "Administrator",
 "permissions": [],
 "sort_field": "modified",
 "sort_order": "DESC",
 "states": []
}